[
  {
    "id": 82,
    "number": "第八十二籤",
    "title": "炎炎烈火焰燒天",
    "level": "中中籤",
    "poem": "炎炎烈火焰燒天，焰裏還生一朵蓮；到底永成根不壞，依然生葉色新鮮。",
    "explanation": "本籤喻，事情逢遇逆境的衝擊，這必須以堅強的毅力堅持，若能熬過種種難關，還能保有這份經營情操，未來還是可以再萌芽發展，並邁向光明前途。",
    "meaning": "炎炎烈火燒天之象，凡事先難後易。",
    "analysis": {
      "家宅": "興旺",
      "自身": "及時",
      "求財": "大吉",
      "交易": "成就",
      "婚姻": "和合",
      "六甲": "生男",
      "行人": "動",
      "田蠶": "利",
      "六畜": "利",
      "尋人": "及時",
      "公訟": "有理",
      "移徙": "吉",
      "失物": "求",
      "疾病": "還願",
      "山墳": "吉"
    }
  },
  {
    "id": 1,
    "number": "第一籤",
    "title": "天開地闢結良緣",
    "level": "上上籤",
    "poem": "天開地闢結良緣，日照中天萬物全；環境清新常得利，平生快樂似神仙。",
    "explanation": "此籤表示時運亨通，事事如意，正是大顯身手的好時機。",
    "meaning": "萬物更生之象，凡事大利。",
    "analysis": {
      "家宅": "祈福",
      "自身": "平順",
      "求財": "有",
      "交易": "成",
      "婚姻": "合",
      "六甲": "生男",
      "行人": "至",
      "田蠶": "熟",
      "六畜": "旺",
      "尋人": "見",
      "公訟": "勝",
      "移徙": "吉",
      "失物": "在",
      "疾病": "安",
      "山墳": "吉"
    }
  }
]
